simple_calculator/__init__.py
simple_calculator/simple_calculator.py
simple_cal_1-0.1.1.dist-info/METADATA
simple_cal_1-0.1.1.dist-info/WHEEL
simple_cal_1-0.1.1.dist-info/top_level.txt
simple_cal_1-0.1.1.dist-info/RECORD
