Metadata-Version: 2.1
Name: simple-cal-1
Version: 0.1.1
Summary: Just a simple calculator class that has basic functionality of calculator
Author: Visa
Author-email: ahvisa1@gmail.com
Classifier: Programming Language :: Python :: 3
Classifier: License :: OSI Approved :: MIT License
Classifier: Operating System :: OS Independent
Requires-Python: >=3.8
